dtwsom.py
dtw_som-1.0.9.dist-info/METADATA
dtw_som-1.0.9.dist-info/RECORD
dtw_som-1.0.9.dist-info/WHEEL
dtw_som-1.0.9.dist-info/top_level.txt
